attrobj/__init__.py
attrobj-0.2.0.dist-info/METADATA
attrobj-0.2.0.dist-info/WHEEL
attrobj-0.2.0.dist-info/top_level.txt
attrobj-0.2.0.dist-info/RECORD
